{
    "description": "",
    "tags": [],
    "size": {
        "height": 440,
        "width": 730
    },
    "objects": [
        {
            "id": 74865782,
            "classId": 6488144,
            "description": "",
            "geometryType": "rectangle",
            "labelerLogin": "inbox@datasetninja.com",
            "createdAt": "2023-10-18T11:00:31.668Z",
            "updatedAt": "2023-10-18T11:00:31.668Z",
            "tags": [],
            "classTitle": "van",
            "points": {
                "exterior": [
                    [
                        57,
                        37
                    ],
                    [
                        678,
                        421
                    ]
                ],
                "interior": []
            }
        }
    ]
}