{
    "description": "",
    "tags": [],
    "size": {
        "height": 500,
        "width": 370
    },
    "objects": [
        {
            "id": 74866071,
            "classId": 6488143,
            "description": "",
            "geometryType": "rectangle",
            "labelerLogin": "inbox@datasetninja.com",
            "createdAt": "2023-10-18T11:00:52.078Z",
            "updatedAt": "2023-10-18T11:00:52.078Z",
            "tags": [],
            "classTitle": "motorbike",
            "points": {
                "exterior": [
                    [
                        23,
                        54
                    ],
                    [
                        352,
                        497
                    ]
                ],
                "interior": []
            }
        }
    ]
}