{
    "description": "",
    "tags": [],
    "size": {
        "height": 290,
        "width": 500
    },
    "objects": [
        {
            "id": 74866188,
            "classId": 6488143,
            "description": "",
            "geometryType": "rectangle",
            "labelerLogin": "inbox@datasetninja.com",
            "createdAt": "2023-10-18T11:00:59.677Z",
            "updatedAt": "2023-10-18T11:00:59.677Z",
            "tags": [],
            "classTitle": "motorbike",
            "points": {
                "exterior": [
                    [
                        51,
                        101
                    ],
                    [
                        292,
                        231
                    ]
                ],
                "interior": []
            }
        }
    ]
}