{
    "description": "",
    "tags": [],
    "size": {
        "height": 727,
        "width": 1000
    },
    "objects": [
        {
            "id": 74867900,
            "classId": 6488142,
            "description": "",
            "geometryType": "rectangle",
            "labelerLogin": "inbox@datasetninja.com",
            "createdAt": "2023-10-18T11:03:15.633Z",
            "updatedAt": "2023-10-18T11:03:15.633Z",
            "tags": [],
            "classTitle": "truck",
            "points": {
                "exterior": [
                    [
                        46,
                        71
                    ],
                    [
                        948,
                        690
                    ]
                ],
                "interior": []
            }
        }
    ]
}