{
    "description": "",
    "tags": [],
    "size": {
        "height": 570,
        "width": 760
    },
    "objects": [
        {
            "id": 74868129,
            "classId": 6488140,
            "description": "",
            "geometryType": "rectangle",
            "labelerLogin": "inbox@datasetninja.com",
            "createdAt": "2023-10-18T11:03:41.163Z",
            "updatedAt": "2023-10-18T11:03:41.163Z",
            "tags": [],
            "classTitle": "threewheel",
            "points": {
                "exterior": [
                    [
                        155,
                        47
                    ],
                    [
                        675,
                        568
                    ]
                ],
                "interior": []
            }
        }
    ]
}